<?xml version="1.0" encoding="UTF-8" standalone="no" ?>
<Application>

  <Header>
    <Version val="13030.00"/>
    <WithIsn val="Y"/>
    <Exe comp="-1"/>
    <LastIsn val="1"/>
    <LastIsnFolder val="0"/>
    <Folders/>
  </Header>

  <DataSourceRepository>
    <DataObjects>
      <DataObject PhysicalName="LC_LIVRO" Resident="N" UniqueISNConvState="12" data_source="CIGAM_SQL" id="1" length="24465" name="LC_LIVRO" offset="212"/>
    </DataObjects>
  </DataSourceRepository>

  <LastModified val="30847881-208086707"/>

</Application>
